pygamescript/__init__.py
pygamescript/algo.py
pygamescript/gamescript.py
pygamescript/template.py
pygamescript-2.0.1.dist-info/METADATA
pygamescript-2.0.1.dist-info/WHEEL
pygamescript-2.0.1.dist-info/top_level.txt
pygamescript-2.0.1.dist-info/RECORD
