Metadata-Version: 2.1
Name: pygamescript
Version: 2.0.1
Summary: Android Auto Pypi
Home-page: https://github.com/NakanoSanku/gamescript
Author: KateTseng
Author-email: Kate.TsengK@outlook.com
License: MIT
Keywords: Android
Requires-Python: >=3
Requires-Dist: minidevice
Requires-Dist: minicv
